{
  "project_info": {
    "project_number": "827732544736",
    "project_id": "costa-engineer-app",
    "storage_bucket": "costa-engineer-app.firebasestorage.app"
  },
  "client": [
    {
      "client_info": {
        "mobilesdk_app_id": "1:827732544736:android:a002665aab80562bcd9485",
        "android_client_info": {
          "package_name": "com.brewinnovate.costatoolbox"
        }
      },
      "oauth_client": [],
      "api_key": [
        {
          "current_key": "AIzaSyCjZWMY3XbWE6CGu5jbJNWmRyIO4UV_7DE"
        }
      ],
      "services": {
        "appinvite_service": {
          "other_platform_oauth_client": []
        }
      }
    }
  ],
  "configuration_version": "1"
}